proj25/__init__.py
proj25-0.1.0.dist-info/METADATA
proj25-0.1.0.dist-info/WHEEL
proj25-0.1.0.dist-info/RECORD
