Metadata-Version: 2.3
Name: proj25
Version: 0.1.0
Summary: 
Author: Дмитрий Лысаков
Author-email: dsl@stack.net
Requires-Python: >=3.12
Classifier: Programming Language :: Python :: 3
Classifier: Programming Language :: Python :: 3.12
Classifier: Programming Language :: Python :: 3.13
Requires-Dist: pyyaml (>=6.0.2,<7.0.0)
